README.txt
setup.py
zChainer/__init__.py
zChainer/autoencoder.py
zChainer/manager.py
zChainer/utility.py
zChainer.egg-info/PKG-INFO
zChainer.egg-info/SOURCES.txt
zChainer.egg-info/dependency_links.txt
zChainer.egg-info/requires.txt
zChainer.egg-info/top_level.txt