Metadata-Version: 1.1
Name: zChainer
Version: 0.3.2
Summary: scikit-learn like interface and stacked autoencoder for chainer
Home-page: https://github.com/shoya140/zChainer
Author: Shoya Ishimaru
Author-email: shoya.ishimaru@gmail.com
License: MIT
Keywords: deep neural network,machine learning
Platform: UNKNOWN
Classifier: Programming Language :: Python :: 2.7
Classifier: Intended Audience :: Science/Research
Classifier: License :: OSI Approved :: MIT License
